capter/__init__.py
capter-1.0.0.dist-info/LICENSE
capter-1.0.0.dist-info/METADATA
capter-1.0.0.dist-info/WHEEL
capter-1.0.0.dist-info/entry_points.txt
capter-1.0.0.dist-info/top_level.txt
capter-1.0.0.dist-info/RECORD
