Metadata-Version: 2.1
Name: capter
Version: 1.0.0
Summary: A small utility to capture the current terminal window and put the image to the clipboard to easily share the output.
Author-email: Deepak Dewani <kumard8308887772@gmail.com>
License: MIT License
Project-URL: Homepage, https://github.com/deepakkumardewani/capter
Classifier: Programming Language :: Python :: 3
Classifier: License :: OSI Approved :: MIT License
Classifier: Operating System :: MacOS
Requires-Python: >=3.8
License-File: LICENSE
Requires-Dist: click
Requires-Dist: pyobjc-framework-Quartz
Requires-Dist: screenshot
